{
  "id": "8a4718e2-9b1f-42e5-897f-0a5aa28361fc",
  "prevId": "00000000-0000-0000-0000-000000000000",
  "version": "7",
  "dialect": "postgresql",
  "tables": {
    "public.creators": {
      "name": "creators",
      "schema": "",
      "columns": {
        "id": {
          "name": "id",
          "type": "uuid",
          "primaryKey": true,
          "notNull": true,
          "default": "gen_random_uuid()"
        },
        "handle": {
          "name": "handle",
          "type": "varchar(64)",
          "primaryKey": false,
          "notNull": true
        },
        "display_name": {
          "name": "display_name",
          "type": "varchar(120)",
          "primaryKey": false,
          "notNull": true
        },
        "tagline": {
          "name": "tagline",
          "type": "varchar(240)",
          "primaryKey": false,
          "notNull": false
        },
        "bio": {
          "name": "bio",
          "type": "text",
          "primaryKey": false,
          "notNull": false
        },
        "wallet": {
          "name": "wallet",
          "type": "varchar(64)",
          "primaryKey": false,
          "notNull": true
        },
        "token_mint": {
          "name": "token_mint",
          "type": "varchar(64)",
          "primaryKey": false,
          "notNull": false
        },
        "token_ticker": {
          "name": "token_ticker",
          "type": "varchar(24)",
          "primaryKey": false,
          "notNull": false
        },
        "token_name": {
          "name": "token_name",
          "type": "varchar(120)",
          "primaryKey": false,
          "notNull": false
        },
        "token_image_url": {
          "name": "token_image_url",
          "type": "text",
          "primaryKey": false,
          "notNull": false
        },
        "token_decimals": {
          "name": "token_decimals",
          "type": "integer",
          "primaryKey": false,
          "notNull": false,
          "default": 9
        },
        "partner_bps": {
          "name": "partner_bps",
          "type": "integer",
          "primaryKey": false,
          "notNull": false,
          "default": 100
        },
        "accent_color": {
          "name": "accent_color",
          "type": "varchar(16)",
          "primaryKey": false,
          "notNull": false,
          "default": "'#C1272D'"
        },
        "created_at": {
          "name": "created_at",
          "type": "timestamp with time zone",
          "primaryKey": false,
          "notNull": true,
          "default": "now()"
        },
        "updated_at": {
          "name": "updated_at",
          "type": "timestamp with time zone",
          "primaryKey": false,
          "notNull": true,
          "default": "now()"
        }
      },
      "indexes": {
        "creators_wallet_idx": {
          "name": "creators_wallet_idx",
          "columns": [
            {
              "expression": "wallet",
              "isExpression": false,
              "asc": true,
              "nulls": "last"
            }
          ],
          "isUnique": false,
          "concurrently": false,
          "method": "btree",
          "with": {}
        },
        "creators_mint_idx": {
          "name": "creators_mint_idx",
          "columns": [
            {
              "expression": "token_mint",
              "isExpression": false,
              "asc": true,
              "nulls": "last"
            }
          ],
          "isUnique": false,
          "concurrently": false,
          "method": "btree",
          "with": {}
        }
      },
      "foreignKeys": {},
      "compositePrimaryKeys": {},
      "uniqueConstraints": {
        "creators_handle_unique": {
          "name": "creators_handle_unique",
          "nullsNotDistinct": false,
          "columns": [
            "handle"
          ]
        }
      },
      "policies": {},
      "checkConstraints": {},
      "isRLSEnabled": false
    },
    "public.files": {
      "name": "files",
      "schema": "",
      "columns": {
        "id": {
          "name": "id",
          "type": "uuid",
          "primaryKey": true,
          "notNull": true,
          "default": "gen_random_uuid()"
        },
        "tier_id": {
          "name": "tier_id",
          "type": "uuid",
          "primaryKey": false,
          "notNull": true
        },
        "filename": {
          "name": "filename",
          "type": "varchar(256)",
          "primaryKey": false,
          "notNull": true
        },
        "storage_key": {
          "name": "storage_key",
          "type": "text",
          "primaryKey": false,
          "notNull": true
        },
        "content_type": {
          "name": "content_type",
          "type": "varchar(128)",
          "primaryKey": false,
          "notNull": false
        },
        "size_bytes": {
          "name": "size_bytes",
          "type": "bigint",
          "primaryKey": false,
          "notNull": false
        },
        "created_at": {
          "name": "created_at",
          "type": "timestamp with time zone",
          "primaryKey": false,
          "notNull": true,
          "default": "now()"
        }
      },
      "indexes": {},
      "foreignKeys": {
        "files_tier_id_tiers_id_fk": {
          "name": "files_tier_id_tiers_id_fk",
          "tableFrom": "files",
          "tableTo": "tiers",
          "columnsFrom": [
            "tier_id"
          ],
          "columnsTo": [
            "id"
          ],
          "onDelete": "cascade",
          "onUpdate": "no action"
        }
      },
      "compositePrimaryKeys": {},
      "uniqueConstraints": {},
      "policies": {},
      "checkConstraints": {},
      "isRLSEnabled": false
    },
    "public.grants": {
      "name": "grants",
      "schema": "",
      "columns": {
        "id": {
          "name": "id",
          "type": "uuid",
          "primaryKey": true,
          "notNull": true,
          "default": "gen_random_uuid()"
        },
        "holder_id": {
          "name": "holder_id",
          "type": "uuid",
          "primaryKey": false,
          "notNull": true
        },
        "tier_id": {
          "name": "tier_id",
          "type": "uuid",
          "primaryKey": false,
          "notNull": true
        },
        "plugin_id": {
          "name": "plugin_id",
          "type": "plugin_id",
          "typeSchema": "public",
          "primaryKey": false,
          "notNull": true
        },
        "external_ref": {
          "name": "external_ref",
          "type": "varchar(256)",
          "primaryKey": false,
          "notNull": false
        },
        "status": {
          "name": "status",
          "type": "grant_status",
          "typeSchema": "public",
          "primaryKey": false,
          "notNull": true,
          "default": "'active'"
        },
        "granted_at": {
          "name": "granted_at",
          "type": "timestamp with time zone",
          "primaryKey": false,
          "notNull": true,
          "default": "now()"
        },
        "revoked_at": {
          "name": "revoked_at",
          "type": "timestamp with time zone",
          "primaryKey": false,
          "notNull": false
        },
        "error": {
          "name": "error",
          "type": "text",
          "primaryKey": false,
          "notNull": false
        }
      },
      "indexes": {
        "grants_holder_idx": {
          "name": "grants_holder_idx",
          "columns": [
            {
              "expression": "holder_id",
              "isExpression": false,
              "asc": true,
              "nulls": "last"
            }
          ],
          "isUnique": false,
          "concurrently": false,
          "method": "btree",
          "with": {}
        }
      },
      "foreignKeys": {
        "grants_holder_id_holders_id_fk": {
          "name": "grants_holder_id_holders_id_fk",
          "tableFrom": "grants",
          "tableTo": "holders",
          "columnsFrom": [
            "holder_id"
          ],
          "columnsTo": [
            "id"
          ],
          "onDelete": "cascade",
          "onUpdate": "no action"
        },
        "grants_tier_id_tiers_id_fk": {
          "name": "grants_tier_id_tiers_id_fk",
          "tableFrom": "grants",
          "tableTo": "tiers",
          "columnsFrom": [
            "tier_id"
          ],
          "columnsTo": [
            "id"
          ],
          "onDelete": "cascade",
          "onUpdate": "no action"
        }
      },
      "compositePrimaryKeys": {},
      "uniqueConstraints": {},
      "policies": {},
      "checkConstraints": {},
      "isRLSEnabled": false
    },
    "public.holders": {
      "name": "holders",
      "schema": "",
      "columns": {
        "id": {
          "name": "id",
          "type": "uuid",
          "primaryKey": true,
          "notNull": true,
          "default": "gen_random_uuid()"
        },
        "wallet": {
          "name": "wallet",
          "type": "varchar(64)",
          "primaryKey": false,
          "notNull": true
        },
        "creator_id": {
          "name": "creator_id",
          "type": "uuid",
          "primaryKey": false,
          "notNull": true
        },
        "current_tier_id": {
          "name": "current_tier_id",
          "type": "uuid",
          "primaryKey": false,
          "notNull": false
        },
        "last_balance": {
          "name": "last_balance",
          "type": "bigint",
          "primaryKey": false,
          "notNull": false,
          "default": "0"
        },
        "last_verified_at": {
          "name": "last_verified_at",
          "type": "timestamp with time zone",
          "primaryKey": false,
          "notNull": false
        },
        "first_seen_at": {
          "name": "first_seen_at",
          "type": "timestamp with time zone",
          "primaryKey": false,
          "notNull": true,
          "default": "now()"
        }
      },
      "indexes": {
        "holders_wallet_idx": {
          "name": "holders_wallet_idx",
          "columns": [
            {
              "expression": "wallet",
              "isExpression": false,
              "asc": true,
              "nulls": "last"
            }
          ],
          "isUnique": false,
          "concurrently": false,
          "method": "btree",
          "with": {}
        }
      },
      "foreignKeys": {
        "holders_creator_id_creators_id_fk": {
          "name": "holders_creator_id_creators_id_fk",
          "tableFrom": "holders",
          "tableTo": "creators",
          "columnsFrom": [
            "creator_id"
          ],
          "columnsTo": [
            "id"
          ],
          "onDelete": "cascade",
          "onUpdate": "no action"
        },
        "holders_current_tier_id_tiers_id_fk": {
          "name": "holders_current_tier_id_tiers_id_fk",
          "tableFrom": "holders",
          "tableTo": "tiers",
          "columnsFrom": [
            "current_tier_id"
          ],
          "columnsTo": [
            "id"
          ],
          "onDelete": "set null",
          "onUpdate": "no action"
        }
      },
      "compositePrimaryKeys": {},
      "uniqueConstraints": {
        "holders_wallet_creator_uniq": {
          "name": "holders_wallet_creator_uniq",
          "nullsNotDistinct": false,
          "columns": [
            "wallet",
            "creator_id"
          ]
        }
      },
      "policies": {},
      "checkConstraints": {},
      "isRLSEnabled": false
    },
    "public.nonces": {
      "name": "nonces",
      "schema": "",
      "columns": {
        "wallet": {
          "name": "wallet",
          "type": "varchar(64)",
          "primaryKey": false,
          "notNull": true
        },
        "nonce": {
          "name": "nonce",
          "type": "varchar(64)",
          "primaryKey": false,
          "notNull": true
        },
        "created_at": {
          "name": "created_at",
          "type": "timestamp with time zone",
          "primaryKey": false,
          "notNull": true,
          "default": "now()"
        },
        "expires_at": {
          "name": "expires_at",
          "type": "timestamp with time zone",
          "primaryKey": false,
          "notNull": true
        }
      },
      "indexes": {},
      "foreignKeys": {},
      "compositePrimaryKeys": {},
      "uniqueConstraints": {},
      "policies": {},
      "checkConstraints": {},
      "isRLSEnabled": false
    },
    "public.perks": {
      "name": "perks",
      "schema": "",
      "columns": {
        "id": {
          "name": "id",
          "type": "uuid",
          "primaryKey": true,
          "notNull": true,
          "default": "gen_random_uuid()"
        },
        "tier_id": {
          "name": "tier_id",
          "type": "uuid",
          "primaryKey": false,
          "notNull": true
        },
        "plugin_id": {
          "name": "plugin_id",
          "type": "plugin_id",
          "typeSchema": "public",
          "primaryKey": false,
          "notNull": true
        },
        "config": {
          "name": "config",
          "type": "jsonb",
          "primaryKey": false,
          "notNull": true
        },
        "created_at": {
          "name": "created_at",
          "type": "timestamp with time zone",
          "primaryKey": false,
          "notNull": true,
          "default": "now()"
        }
      },
      "indexes": {
        "perks_tier_idx": {
          "name": "perks_tier_idx",
          "columns": [
            {
              "expression": "tier_id",
              "isExpression": false,
              "asc": true,
              "nulls": "last"
            }
          ],
          "isUnique": false,
          "concurrently": false,
          "method": "btree",
          "with": {}
        }
      },
      "foreignKeys": {
        "perks_tier_id_tiers_id_fk": {
          "name": "perks_tier_id_tiers_id_fk",
          "tableFrom": "perks",
          "tableTo": "tiers",
          "columnsFrom": [
            "tier_id"
          ],
          "columnsTo": [
            "id"
          ],
          "onDelete": "cascade",
          "onUpdate": "no action"
        }
      },
      "compositePrimaryKeys": {},
      "uniqueConstraints": {},
      "policies": {},
      "checkConstraints": {},
      "isRLSEnabled": false
    },
    "public.sessions": {
      "name": "sessions",
      "schema": "",
      "columns": {
        "id": {
          "name": "id",
          "type": "uuid",
          "primaryKey": true,
          "notNull": true,
          "default": "gen_random_uuid()"
        },
        "wallet": {
          "name": "wallet",
          "type": "varchar(64)",
          "primaryKey": false,
          "notNull": true
        },
        "role": {
          "name": "role",
          "type": "varchar(16)",
          "primaryKey": false,
          "notNull": true,
          "default": "'holder'"
        },
        "creator_id": {
          "name": "creator_id",
          "type": "uuid",
          "primaryKey": false,
          "notNull": false
        },
        "expires_at": {
          "name": "expires_at",
          "type": "timestamp with time zone",
          "primaryKey": false,
          "notNull": true
        },
        "created_at": {
          "name": "created_at",
          "type": "timestamp with time zone",
          "primaryKey": false,
          "notNull": true,
          "default": "now()"
        }
      },
      "indexes": {},
      "foreignKeys": {
        "sessions_creator_id_creators_id_fk": {
          "name": "sessions_creator_id_creators_id_fk",
          "tableFrom": "sessions",
          "tableTo": "creators",
          "columnsFrom": [
            "creator_id"
          ],
          "columnsTo": [
            "id"
          ],
          "onDelete": "cascade",
          "onUpdate": "no action"
        }
      },
      "compositePrimaryKeys": {},
      "uniqueConstraints": {},
      "policies": {},
      "checkConstraints": {},
      "isRLSEnabled": false
    },
    "public.tiers": {
      "name": "tiers",
      "schema": "",
      "columns": {
        "id": {
          "name": "id",
          "type": "uuid",
          "primaryKey": true,
          "notNull": true,
          "default": "gen_random_uuid()"
        },
        "creator_id": {
          "name": "creator_id",
          "type": "uuid",
          "primaryKey": false,
          "notNull": true
        },
        "name": {
          "name": "name",
          "type": "varchar(64)",
          "primaryKey": false,
          "notNull": true
        },
        "description": {
          "name": "description",
          "type": "text",
          "primaryKey": false,
          "notNull": false
        },
        "threshold": {
          "name": "threshold",
          "type": "bigint",
          "primaryKey": false,
          "notNull": true
        },
        "position": {
          "name": "position",
          "type": "integer",
          "primaryKey": false,
          "notNull": true,
          "default": 0
        },
        "created_at": {
          "name": "created_at",
          "type": "timestamp with time zone",
          "primaryKey": false,
          "notNull": true,
          "default": "now()"
        }
      },
      "indexes": {
        "tiers_creator_idx": {
          "name": "tiers_creator_idx",
          "columns": [
            {
              "expression": "creator_id",
              "isExpression": false,
              "asc": true,
              "nulls": "last"
            },
            {
              "expression": "position",
              "isExpression": false,
              "asc": true,
              "nulls": "last"
            }
          ],
          "isUnique": false,
          "concurrently": false,
          "method": "btree",
          "with": {}
        }
      },
      "foreignKeys": {
        "tiers_creator_id_creators_id_fk": {
          "name": "tiers_creator_id_creators_id_fk",
          "tableFrom": "tiers",
          "tableTo": "creators",
          "columnsFrom": [
            "creator_id"
          ],
          "columnsTo": [
            "id"
          ],
          "onDelete": "cascade",
          "onUpdate": "no action"
        }
      },
      "compositePrimaryKeys": {},
      "uniqueConstraints": {},
      "policies": {},
      "checkConstraints": {},
      "isRLSEnabled": false
    },
    "public.web_content": {
      "name": "web_content",
      "schema": "",
      "columns": {
        "id": {
          "name": "id",
          "type": "uuid",
          "primaryKey": true,
          "notNull": true,
          "default": "gen_random_uuid()"
        },
        "tier_id": {
          "name": "tier_id",
          "type": "uuid",
          "primaryKey": false,
          "notNull": true
        },
        "kind": {
          "name": "kind",
          "type": "varchar(32)",
          "primaryKey": false,
          "notNull": true
        },
        "url": {
          "name": "url",
          "type": "text",
          "primaryKey": false,
          "notNull": true
        },
        "title": {
          "name": "title",
          "type": "varchar(240)",
          "primaryKey": false,
          "notNull": false
        },
        "description": {
          "name": "description",
          "type": "text",
          "primaryKey": false,
          "notNull": false
        },
        "created_at": {
          "name": "created_at",
          "type": "timestamp with time zone",
          "primaryKey": false,
          "notNull": true,
          "default": "now()"
        }
      },
      "indexes": {},
      "foreignKeys": {
        "web_content_tier_id_tiers_id_fk": {
          "name": "web_content_tier_id_tiers_id_fk",
          "tableFrom": "web_content",
          "tableTo": "tiers",
          "columnsFrom": [
            "tier_id"
          ],
          "columnsTo": [
            "id"
          ],
          "onDelete": "cascade",
          "onUpdate": "no action"
        }
      },
      "compositePrimaryKeys": {},
      "uniqueConstraints": {},
      "policies": {},
      "checkConstraints": {},
      "isRLSEnabled": false
    }
  },
  "enums": {
    "public.grant_status": {
      "name": "grant_status",
      "schema": "public",
      "values": [
        "active",
        "revoked",
        "error"
      ]
    },
    "public.plugin_id": {
      "name": "plugin_id",
      "schema": "public",
      "values": [
        "web",
        "files",
        "telegram",
        "email"
      ]
    }
  },
  "schemas": {},
  "sequences": {},
  "roles": {},
  "policies": {},
  "views": {},
  "_meta": {
    "columns": {},
    "schemas": {},
    "tables": {}
  }
}